Metadata-Version: 2.1
Name: debuglogs
Version: 0.1.0
Summary: A package for easy colored debug logs.
Home-page: https://github.com/Gasterbuzzer/DebugLogs
Author: Gasterbuzzer
Classifier: Intended Audience :: Developers
Classifier: Programming Language :: Python
Classifier: Programming Language :: Python :: 3
License-File: LICENSE
